springcraft/__init__.py
springcraft/anm.py
springcraft/data/d_enm.csv
springcraft/data/d_enm_edges.csv
springcraft/data/keskin.csv
springcraft/data/miyazawa.csv
springcraft/data/s_enm_10.csv
springcraft/data/s_enm_13.csv
springcraft/data/sd_enm.csv
springcraft/forcefield.py
springcraft/gnm.py
springcraft/interaction.py
springcraft/nma.py
springcraft-0.3.0.dist-info/LICENSE
springcraft-0.3.0.dist-info/WHEEL
springcraft-0.3.0.dist-info/METADATA
springcraft-0.3.0.dist-info/RECORD
