Metadata-Version: 2.1
Name: springcraft
Version: 0.3.0
Summary: Investigate molecular dynamics with elastic network models
Home-page: https://springcraft.biotite-python.org
License: BSD-3-Clause
Keywords: Bioinformatics,Computational biology,Elastic network models,Normal mode analysis
Author: Patrick Kunzmann
Author-email: padix.key@gmail.com
Requires-Python: >=3.7,<4.0
Classifier: Development Status :: 4 - Beta
Classifier: Intended Audience :: Science/Research
Classifier: License :: OSI Approved :: BSD License
Classifier: Natural Language :: English
Classifier: Operating System :: MacOS
Classifier: Operating System :: Microsoft :: Windows
Classifier: Operating System :: POSIX :: Linux
Classifier: Programming Language :: Python :: 3
Classifier: Programming Language :: Python :: 3.10
Classifier: Programming Language :: Python :: 3.7
Classifier: Programming Language :: Python :: 3.8
Classifier: Programming Language :: Python :: 3.9
Classifier: Topic :: Scientific/Engineering :: Bio-Informatics
Requires-Dist: biotite (>=0.32)
Requires-Dist: numpy (>=1.15,<2.0)
Project-URL: Documentation, https://springcraft.biotite-python.org
Project-URL: Repository, https://github.com/biotite-dev/springcraft
